quicksearch/__init__.py
quicksearch/_version.py
quicksearch/async_batch_processor.py
quicksearch/async_client.py
quicksearch/batch_processor.py
quicksearch/client.py
quicksearch/exceptions.py
quicksearch/models.py
quicksearch/sync_client.py
quicksearch_python_sdk-1.0.4.dist-info/METADATA
quicksearch_python_sdk-1.0.4.dist-info/WHEEL
quicksearch_python_sdk-1.0.4.dist-info/licenses/LICENSE
quicksearch_python_sdk-1.0.4.dist-info/RECORD
