Metadata-Version: 2.4
Name: quicksearch-python-sdk
Version: 1.0.4
Summary: Python SDK for QuickSearch event log storage system
Project-URL: Homepage, https://github.com/quicksearch/quicksearch-python-sdk
Project-URL: Repository, https://github.com/quicksearch/quicksearch-python-sdk
Project-URL: Issues, https://github.com/quicksearch/quicksearch-python-sdk/issues
Author: QuickSearch Team
License: MIT
License-File: LICENSE
Keywords: api-client,events,logging,search,syslog
Classifier: Development Status :: 3 - Alpha
Classifier: Intended Audience :: Developers
Classifier: License :: OSI Approved :: MIT License
Classifier: Programming Language :: Python :: 3
Classifier: Programming Language :: Python :: 3.9
Classifier: Programming Language :: Python :: 3.10
Classifier: Programming Language :: Python :: 3.11
Classifier: Programming Language :: Python :: 3.12
Classifier: Topic :: Software Development :: Libraries :: Python Modules
Classifier: Topic :: System :: Logging
Requires-Python: >=3.9
Requires-Dist: httpx>=0.28.1
Requires-Dist: pydantic>=2.11.7
Provides-Extra: dev
Requires-Dist: black>=24.10.0; extra == 'dev'
Requires-Dist: mypy>=1.19.1; extra == 'dev'
Requires-Dist: pytest-asyncio>=1.0.0; extra == 'dev'
Requires-Dist: pytest-cov>=7.0.0; extra == 'dev'
Requires-Dist: pytest-mock>=3.15.1; extra == 'dev'
Requires-Dist: pytest>=8.4.0; extra == 'dev'
Requires-Dist: respx>=0.22.0; extra == 'dev'
Requires-Dist: ruff>=0.13.1; extra == 'dev'
